dizge/__init__.py
dizge/analyzer.py
dizge/competence/__init__.py
dizge/competence/lexicon.py
dizge/competence/phonology.py
dizge/tools/__init__.py
dizge/tools/phonology.py
dizge-0.1.6.dist-info/LICENSE
dizge-0.1.6.dist-info/METADATA
dizge-0.1.6.dist-info/WHEEL
dizge-0.1.6.dist-info/top_level.txt
dizge-0.1.6.dist-info/RECORD
