Metadata-Version: 2.1
Name: dizge
Version: 0.1.6
Summary: The grammar analyzer for Turkish
Home-page: https://github.com/dizge/dizge
Author-email: dizgenlp@gmail.com
License: MIT
Keywords: python,nlp,linguistics,phonology,turkish,grammar
Classifier: License :: OSI Approved :: MIT License
Classifier: Intended Audience :: Developers
Classifier: Intended Audience :: Education
Classifier: Intended Audience :: Information Technology
Classifier: Intended Audience :: Science/Research
Classifier: Programming Language :: Python :: 3.12
License-File: LICENSE
